Lab1/alu.v
`timescale 1ns / 100ps

module ALU(A,B,OP,C,Cout);

	input [15:0]A;
	input [15:0]B;
	input [3:0]OP;
	output [15:0]C;
	output Cout;

	//TODO
	reg reg_Cout;
	reg [15:0]reg_C;
	wire msbA;
	wire msbB;
	assign C = reg_C;
	assign Cout = reg_Cout;
	assign msbA = A[15];
	assign msbB = B[15];
	always @ (*) begin
		case (OP)
			4'b0000: //A+B
				begin
					reg_C = A+B;
					if((msbA == 1'b0)&(msbB == 1'b0)&(reg_C[15] == 1'b1)) begin
						reg_Cout = 1'b1;
					end
					if((msbA == 1'b1)&(msbB == 1'b1)&(reg_C[15] == 1'b0))begin
						reg_Cout = 1'b1;
					end
					else begin
						reg_Cout = 1'b0;
					end
				end
			4'b0001: //A-B
				begin
					reg_C = A-B;
					if((msbA == 1'b0)&(msbB == 1'b1)&(reg_C[15] == 1'b1)) begin
						reg_Cout = 1'b1;
					end
					if((msbA == 1'b1)&(msbB == 1'b0)&(reg_C[15] == 1'b0))begin
						reg_Cout = 1'b1;
					end
					else begin
						reg_Cout = 1'b0;
					end
				end
			4'b0010: // A and B
				begin
					reg_C= A&B;
					reg_Cout = 1'b0;
				end
			4'b0011: // A or B
				begin
					reg_C= A|B;
					reg_Cout = 1'b0;
				end
			4'b0100: // A nand B
				begin
					reg_C= ~(A&B);
					reg_Cout = 1'b0;
				end
			4'b0101: // A nor B
				begin
					reg_C= ~(A|B);
					reg_Cout = 1'b0;
				end
 			4'b0110: // A xor B
			 	begin
					reg_C = A^B;
					reg_Cout = 1'b0;
				end
			4'b0111: // A xnor B
				begin
					reg_C = ~(A^B);
					reg_Cout = 1'b0;
				end
			4'b1000: // identity
				begin
					reg_C = A;
					reg_Cout = 1'b0;
				end
			4'b1001: // ~A not
				begin
					reg_C = ~A;
					reg_Cout = 1'b0;
				end
			4'b1010: // A >> 1 logical
				begin
					reg_C = {1'b0, A[15:1]};
					reg_Cout = 1'b0;
				end
			4'b1011: // A >>> 1 arithmetic
				begin
					reg_C = {A[15], A[15:1]};
					reg_Cout = 1'b0;
				end
			4'b1100: // rotate right
				begin
					reg_C = {A[0], A[15:1]};
					reg_Cout = 1'b0;
				end
			4'b1101: // A << 1 
				begin
					reg_C = {A[14:0], 1'b0};
					reg_Cout = 1'b0;
				end
			4'b1110: // A <<< 1
				begin
					reg_C = {A[14:0], A[0]};
					reg_Cout = 1'b0;
				end
			4'b1111: // rotate left
				begin
					reg_C = {A[14:0], A[15]};
					reg_Cout = 1'b0;
				end
		endcase
	end

endmodule

Lab1/ALU_TB.v
`timescale 100ps / 100ps
`include "alu.v"

// Arithmetic
`define	OP_ADD	4'b0000
`define	OP_SUB	4'b0001
// Bitwise Boolean operation
`define	OP_AND	4'b0010
`define	OP_OR 	4'b0011
`define	OP_NAND	4'b0100
`define	OP_NOR	4'b0101
`define	OP_XOR	4'b0110
`define	OP_XNOR	4'b0111
// Logic
`define	OP_ID	  4'b1000
`define	OP_NOT  4'b1001

// Shift
`define	OP_LRS	4'b1010
`define	OP_ARS	4'b1011
`define	OP_RR	  4'b1100
`define	OP_LLS	4'b1101
`define	OP_ALS	4'b1110
`define	OP_RL	  4'b1111

module ALU_TB;

//Internal signals declarations:
reg [15:0]A;
reg [15:0]B;
reg [3:0]OP;
wire [15:0]C;
wire Cout;

reg [15:0] Passed;
reg [15:0] Failed;

// Unit Under Test port map
	ALU UUT (
		.A(A),
		.B(B),
		.OP(OP),
		.C(C),
		.Cout(Cout));


initial
begin
	$dumpfile("test_out.vcd");
	$dumpvars(-1,UUT);
end

initial begin
	Passed = 0;
	Failed = 0;

	ArithmeticTest;
	BitwiseBooleanTest;
	ShiftTest;

	$display("Passed = %0d, Failed = %0d", Passed, Failed);
	$finish;
end

task ArithmeticTest;
begin
	AddTest;
	SubTest;
end
endtask

task BitwiseBooleanTest;
begin
	AndTest;
	OrTest;
	NandTest;
	NorTest;
	XorTest;
	XnorTest;
	IdTest;
	NotTest;
end
endtask

task ShiftTest;
begin
	LrsTest;
	ArsTest;
	RrTest;
	LlsTest;
	AlsTest;
	RlTest;
end
endtask

task AddTest;
begin
	OP = `OP_ADD;

	Test("Add-1", 0, 0, 0, 0);
	Test("Add-2", 1, 0, 1, 0);
	Test("Add-3", 2, 3, 5, 0);
	Test("Add-4", 3, 2, 5, 0);
	Test("Add-5", 2, 3, 5, 0);
	Test("Add-6", 3, 2, 5, 0);
	Test("Add-7", 16'h8000, 16'h8000, 0, 1);
	Test("Add-8", 16'hffff, 1, 0, 0);
	Test("Add-9", 16'hffff, 16'hffff, 16'hfffe, 0);
end
endtask

task SubTest;
begin
	OP = `OP_SUB;
	Test("Sub-1", 0, 0, 0, 0);
	Test("Sub-2", 1, 0, 1, 0);
	Test("Sub-3", 0, 1, 16'hffff, 0);
	Test("Sub-4", 16'hffff, 16'hffff, 0, 0);
	Test("Sub-5", 3, 2, 1, 0);
	Test("Sub-6", 0, 2, 16'hfffe, 0);
	Test("Sub-7", 0, 16'hffff, 1, 0);
end
endtask

task IdTest;
begin
	OP = `OP_ID;
	Test("Id-1", 0, 0, 0, 0);
	Test("Id-2", 16'hdead, 0, 16'hdead, 0);
	Test("Id-3", 16'hbeef, 0, 16'hbeef, 0);
end
endtask

task NandTest;
begin
	OP = `OP_NAND;
	Test("Nand-1", {4{4'b1010}}, {4{4'b0101}}, {4{4'b1111}}, 0);
	Test("Nand-2", {4{4'b0110}}, {4{4'b0101}}, {4{4'b1011}}, 0);
end
endtask

task NorTest;
begin
	OP = `OP_NOR;
	Test("Nor-1", {4{4'b0101}}, {4{4'b1101}}, {4{4'b0010}}, 0);
	Test("Nor-2", {4{4'b1000}}, {4{4'b0001}}, {4{4'b0110}}, 0);
end
endtask

task XnorTest;
begin
	OP = `OP_XNOR;
	Test("Xnor-1", {4{4'b0111}}, {4{4'b0001}}, {4{4'b1001}}, 0);
	Test("Xnor-2", {4{4'b1010}}, {4{4'b0101}}, {4{4'b0000}}, 0);
end
endtask

task NotTest;
begin
	OP = `OP_NOT;
	Test("Not-1", 0, 0, 16'hffff, 0);
	Test("Not-2", 1, 0, 16'hfffe, 0);
	Test("Not-3", 16'hcafe, 0, 16'h3501, 0);
end
endtask

task AndTest;
begin
	OP = `OP_AND;
	Test("And-1", {4{4'b0111}}, {4{4'b0101}}, {4{4'b0101}}, 0);
	Test("And-2", {4{4'b1010}}, {4{4'b0101}}, {4{4'b0000}}, 0);
end
endtask

task OrTest;
begin
	OP = `OP_OR;
	Test("Or-1", {4{4'b0111}}, {4{4'b0101}}, {4{4'b0111}}, 0);
	Test("Or-2", {4{4'b1010}}, {4{4'b0101}}, {4{4'b1111}}, 0);
end
endtask

task XorTest;
begin
	OP = `OP_XOR;
	Test("Xor-1", {4{4'b0111}}, {4{4'b0101}}, {4{4'b0010}}, 0);
	Test("Xor-2", {4{4'b1010}}, {4{4'b0101}}, {4{4'b1111}}, 0);
end
endtask

task LrsTest;
begin
	OP = `OP_LRS;
	Test("Lrs-1", 16'ha, 0, 5, 0);
	Test("Lrs-2", 1, 0, 0, 0);
	Test("Lrs-3", 16'hfffa, 0, 16'h7ffd, 0);
	Test("Lrs-4", 16'hffff, 0, 16'h7fff, 0);
end
endtask

task ArsTest;
begin
	OP = `OP_ARS;
	Test("Ars-1", 16'ha, 0, 5, 0);
	Test("Ars-2", 1, 0, 0, 0);
	Test("Ars-3", 16'hfffa, 0, 16'hfffd, 0);
	Test("Ars-4", 16'hffff, 0, 16'hffff, 0);
end
endtask

task RrTest;
begin
	OP = `OP_RR;
	Test("Rr-1", 16'ha, 0, 16'h5, 0);
	Test("Rr-2", 16'hb, 0, 16'h8005, 0);
end
endtask

task LlsTest;
begin
	OP = `OP_LLS;
	Test("Lls-1", 16'ha, 0, 16'h14, 0);
	Test("Lls-2", 16'hf000, 0, 16'he000, 0);
end
endtask

task AlsTest;
begin
	OP = `OP_ALS;
	Test("Als-1", 16'ha, 0, 16'h14, 0);
	Test("Als-2", 16'hf000, 0, 16'he000, 0);
end
endtask

task RlTest;
begin
	OP = `OP_RL;
	Test("Rl-1", 16'h7000, 0, 16'he000, 0);
	Test("Rl-2", 16'hf000, 0, 16'he001, 0);
end
endtask

task Test;
	input [16 * 8 : 0] test_name;
	input [15:0] A_;
	input [15:0] B_;
	input [15:0] C_expected;
	input Cout_expected;
begin
	$display("TEST %s :", test_name);
	A = A_;
	B = B_;
	#1;
	if (C == C_expected && Cout == Cout_expected)
		begin
			$display("PASSED");
			Passed = Passed + 1;
		end
	else
		begin
			$display("FAILED");
			$display("A = %0b, B = %0b, C = %0b (Ans : %0b), Cout = %0b (Ans : %0b)", A_, B_, C, C_expected, Cout, Cout_expected);
			Failed = Failed + 1;
		end
end
endtask

endmodule

Lab1/test_out.vcd
$date
	Sun Sep  5 17:41:22 2021
$end
$version
	Icarus Verilog
$end
$timescale
	100ps
$end
$scope module ALU_TB $end
$scope module UUT $end
$var wire 16 ! A [15:0] $end
$var wire 16 " B [15:0] $end
$var wire 16 # C [15:0] $end
$var wire 1 $ Cout $end
$var wire 4 % OP [3:0] $end
$var wire 1 & msbB $end
$var wire 1 ' msbA $end
$var reg 16 ( reg_C [15:0] $end
$var reg 1 ) reg_Cout $end
$upscope $end
$upscope $end
$enddefinitions $end
#0
$dumpvars
0)
b0 (
0'
0&
b0 %
0$
b0 #
b0 "
b0 !
$end
#10
b1 #
b1 (
b1 !
#20
b101 #
b101 (
b11 "
b10 !
#30
b10 "
b11 !
#40
b11 "
b10 !
#50
b10 "
b11 !
#60
1$
1)
1&
b0 #
b0 (
1'
b1000000000000000 "
b1000000000000000 !
#70
0$
0)
0&
b1 "
b1111111111111111 !
#80
b1111111111111110 #
b1111111111111110 (
1&
b1111111111111111 "
#90
0&
0'
b0 #
b0 (
b0 "
b0 !
b1 %
#100
b1 #
b1 (
b1 !
#110
b1111111111111111 #
b1111111111111111 (
b1 "
b0 !
#120
1&
0$
0)
b0 #
b0 (
1'
b1111111111111111 "
b1111111111111111 !
#130
0&
b1 #
b1 (
0'
b10 "
b11 !
#140
b1111111111111110 #
b1111111111111110 (
b0 !
#150
b1 #
b1 (
1&
b1111111111111111 "
#160
0&
b101010101010101 #
b101010101010101 (
b101010101010101 "
b111011101110111 !
b10 %
#170
b0 #
b0 (
1'
b1010101010101010 !
#180
0'
b111011101110111 #
b111011101110111 (
b111011101110111 !
b11 %
#190
b1111111111111111 #
b1111111111111111 (
1'
b1010101010101010 !
#200
b100 %
#210
b1011101110111011 #
b1011101110111011 (
0'
b110011001100110 !
#220
1&
b10001000100010 #
b10001000100010 (
b1101110111011101 "
b101010101010101 !
b101 %
#230
0&
b110011001100110 #
b110011001100110 (
1'
b1000100010001 "
b1000100010001000 !
#240
0'
b10001000100010 #
b10001000100010 (
b101010101010101 "
b111011101110111 !
b110 %
#250
b1111111111111111 #
b1111111111111111 (
1'
b1010101010101010 !
#260
0'
b1001100110011001 #
b1001100110011001 (
b1000100010001 "
b111011101110111 !
b111 %
#270
b0 #
b0 (
1'
b101010101010101 "
b1010101010101010 !
#280
0'
b0 "
b0 !
b1000 %
#290
b1101111010101101 #
b1101111010101101 (
1'
b1101111010101101 !
#300
b1011111011101111 #
b1011111011101111 (
b1011111011101111 !
#310
0'
b1111111111111111 #
b1111111111111111 (
b0 !
b1001 %
#320
b1111111111111110 #
b1111111111111110 (
b1 !
#330
b11010100000001 #
b11010100000001 (
1'
b1100101011111110 !
#340
0'
b101 #
b101 (
b1010 !
b1010 %
#350
b0 #
b0 (
b1 !
#360
b111111111111101 #
b111111111111101 (
1'
b1111111111111010 !
#370
b111111111111111 #
b111111111111111 (
b1111111111111111 !
#380
0'
b101 #
b101 (
b1010 !
b1011 %
#390
b0 #
b0 (
b1 !
#400
b1111111111111101 #
b1111111111111101 (
1'
b1111111111111010 !
#410
b1111111111111111 #
b1111111111111111 (
b1111111111111111 !
#420
0'
b101 #
b101 (
b1010 !
b1100 %
#430
b1000000000000101 #
b1000000000000101 (
b1011 !
#440
b10100 #
b10100 (
b1010 !
b1101 %
#450
b1110000000000000 #
b1110000000000000 (
1'
b1111000000000000 !
#460
0'
b10100 #
b10100 (
b1010 !
b1110 %
#470
b1110000000000000 #
b1110000000000000 (
1'
b1111000000000000 !
#480
0'
b111000000000000 !
b1111 %
#490
b1110000000000001 #
b1110000000000001 (
1'
b1111000000000000 !
